nAltORFs-0.1.2.data/scripts/bicodon_counts_from_fasta.py
nAltORFs-0.1.2.data/scripts/codon_freq_from_bicodons.py
nAltORFs-0.1.2.data/scripts/find_nested_alt_orfs.py
naltorfs/bicodon_counts_from_fasta.py
naltorfs/codon_freq_from_bicodons.py
naltorfs/find_nested_alt_orfs.py
nAltORFs-0.1.2.dist-info/LICENSE
nAltORFs-0.1.2.dist-info/METADATA
nAltORFs-0.1.2.dist-info/WHEEL
nAltORFs-0.1.2.dist-info/top_level.txt
nAltORFs-0.1.2.dist-info/RECORD
