Metadata-Version: 2.1
Name: nAltORFs
Version: 0.1.2
Summary: nAltORFs is a set of command-line tools for working with Nested Alternate Open Reading Frames.
Home-page: https://github.com/BlankenbergLab/nAltORFs
Author: Blankenberg Lab
Author-email: dan.blankenberg@gmail.com
License: UNKNOWN
Project-URL: Bug Tracker, https://github.com/BlankenbergLab/nAltORFs/issues
Platform: UNKNOWN
Classifier: Programming Language :: Python :: 3
Classifier: License :: OSI Approved :: MIT License
Classifier: Operating System :: OS Independent
Requires-Python: >=3.8
License-File: LICENSE
Requires-Dist: biopython (==1.79)
Requires-Dist: twobitreader (==3.1.7)
